src/hotmart_mcp.py
src/hotmart/__init__.py
src/hotmart/auth.py
src/hotmart/client.py
src/hotmart/config.py
src/hotmart/models.py
src/hotmart/tools.py
src/hotmart/models/__init__.py
src/hotmart/models/base.py
src/hotmart/models/product.py
src/hotmart/models/sale.py
src/hotmart/models/subscription.py
src/hotmart/tools/__init__.py
src/hotmart/tools/base.py
src/hotmart/tools/products.py
src/hotmart/tools/sales.py
src/tests/__init__.py
src/tests/run_tests.py
src/tests/test_auth.py
src/tests/test_client.py
src/tests/test_config.py
src/tests/test_imports.py
src/tests/test_products.py
src/tests/test_runner.py
src/tests/test_sales.py
src/tests/test_sse_poc.py
src/tests/test_tools.py
hotmart_mcp-0.1.0.dist-info/METADATA
hotmart_mcp-0.1.0.dist-info/WHEEL
hotmart_mcp-0.1.0.dist-info/entry_points.txt
hotmart_mcp-0.1.0.dist-info/licenses/LICENSE
hotmart_mcp-0.1.0.dist-info/RECORD
