Metadata-Version: 2.4
Name: hotmart-mcp
Version: 0.1.0
Summary: Model Context Protocol server for Hotmart API integration
Project-URL: Homepage, https://github.com/cajuflow/hotmart-mcp
Project-URL: Repository, https://github.com/cajuflow/hotmart-mcp
Author-email: Vinicius <contato@vdscruz.com>
License: MIT
License-File: LICENSE
Keywords: api,claude,hotmart,mcp
Requires-Python: >=3.11
Requires-Dist: fastapi>=0.104.0
Requires-Dist: httpx>=0.27.0
Requires-Dist: mcp>=1.0.0
Requires-Dist: pydantic>=2.0.0
Requires-Dist: python-dotenv>=1.0.0
Requires-Dist: requests>=2.31.0
Requires-Dist: uvicorn[standard]>=0.24.0
Provides-Extra: dev
Requires-Dist: black>=23.0.0; extra == 'dev'
Requires-Dist: isort>=5.12.0; extra == 'dev'
Requires-Dist: pytest-asyncio>=0.21.0; extra == 'dev'
Requires-Dist: pytest>=7.4.0; extra == 'dev'
